[
  {
    "id": 1,
    "authorName": "John Smith",
    "companyName": "ABC company",
    "testimony": " Lorem ipsum dolor sit amet, consectetur adipisicing elit.Eligendi voluptate tempora qui distinctio consequatur aliquid pariatur cupiditate quas cum fugit."
  },
  {
    "id": 2,
    "authorName": "John Smith",
    "companyName": "ABC company",
    "testimony": " Lorem ipsum dolor sit amet, consectetur adipisicing elit.Eligendi voluptate tempora qui distinctio consequatur aliquid pariatur cupiditate quas cum fugit."
  }
]
